{
  "descriptionHash": "3E504ED7FA8114980B04E7195831F80547184654C146F1FD85AC10CA4C759A619FD8BF9382EB0985F441DC34AE9296C5D30BA29B686775D164498844C14E3A0F",
  "descriptionLocation": "../fixed.json",
  "lockFileVersion": "1.0.0",
  "kiotaVersion": "1.29.0",
  "clientClassName": "TelnyxOpenApiClient",
  "typeAccessModifier": "Public",
  "clientNamespaceName": "Soenneker.Telnyx.OpenApiClient",
  "language": "CSharp",
  "usesBackingStore": false,
  "excludeBackwardCompatible": true,
  "includeAdditionalData": true,
  "disableSSLValidation": false,
  "serializers": [
    "Microsoft.Kiota.Serialization.Json.JsonSerializationWriterFactory",
    "Microsoft.Kiota.Serialization.Text.TextSerializationWriterFactory",
    "Microsoft.Kiota.Serialization.Form.FormSerializationWriterFactory",
    "Microsoft.Kiota.Serialization.Multipart.MultipartSerializationWriterFactory"
  ],
  "deserializers": [
    "Microsoft.Kiota.Serialization.Json.JsonParseNodeFactory",
    "Microsoft.Kiota.Serialization.Text.TextParseNodeFactory",
    "Microsoft.Kiota.Serialization.Form.FormParseNodeFactory"
  ],
  "structuredMimeTypes": [
    "application/json",
    "text/plain;q=0.9",
    "application/x-www-form-urlencoded;q=0.2",
    "multipart/form-data;q=0.1"
  ],
  "includePatterns": [],
  "excludePatterns": [],
  "disabledValidationRules": []
}