{
  "descriptionHash": "8733D27DE4D78B0B760EF6CC45DC89D5EB381B89D9DB8C02914B2468EC409B9F00144E18ADBF002BD150292FDC7CF045AEB96DCAAED262B0DE4750DF9800E398",
  "descriptionLocation": "../fixed.json",
  "lockFileVersion": "1.0.0",
  "kiotaVersion": "1.30.0",
  "clientClassName": "TelnyxOpenApiClient",
  "typeAccessModifier": "Public",
  "clientNamespaceName": "Soenneker.Telnyx.OpenApiClient",
  "language": "CSharp",
  "usesBackingStore": false,
  "excludeBackwardCompatible": true,
  "includeAdditionalData": true,
  "disableSSLValidation": false,
  "serializers": [
    "Microsoft.Kiota.Serialization.Json.JsonSerializationWriterFactory",
    "Microsoft.Kiota.Serialization.Text.TextSerializationWriterFactory",
    "Microsoft.Kiota.Serialization.Form.FormSerializationWriterFactory",
    "Microsoft.Kiota.Serialization.Multipart.MultipartSerializationWriterFactory"
  ],
  "deserializers": [
    "Microsoft.Kiota.Serialization.Json.JsonParseNodeFactory",
    "Microsoft.Kiota.Serialization.Text.TextParseNodeFactory",
    "Microsoft.Kiota.Serialization.Form.FormParseNodeFactory"
  ],
  "structuredMimeTypes": [
    "application/json",
    "text/plain;q=0.9",
    "application/x-www-form-urlencoded;q=0.2",
    "multipart/form-data;q=0.1"
  ],
  "includePatterns": [],
  "excludePatterns": [],
  "disabledValidationRules": []
}