{
  "descriptionHash": "F1C5C3EF21A9031DB9B69031CC8FD4D1AE2209CE0ECDE4637A8D51CEA4225A98D2F9B0261F67A6EFCABE1AD9AF1DAEEA52030B0C8D723E7D0C37855E13271C2B",
  "descriptionLocation": "../fixed.json",
  "lockFileVersion": "1.0.0",
  "kiotaVersion": "1.28.0",
  "clientClassName": "TelnyxOpenApiClient",
  "typeAccessModifier": "Public",
  "clientNamespaceName": "Soenneker.Telnyx.OpenApiClient",
  "language": "CSharp",
  "usesBackingStore": false,
  "excludeBackwardCompatible": true,
  "includeAdditionalData": true,
  "disableSSLValidation": false,
  "serializers": [
    "Microsoft.Kiota.Serialization.Json.JsonSerializationWriterFactory",
    "Microsoft.Kiota.Serialization.Text.TextSerializationWriterFactory",
    "Microsoft.Kiota.Serialization.Form.FormSerializationWriterFactory",
    "Microsoft.Kiota.Serialization.Multipart.MultipartSerializationWriterFactory"
  ],
  "deserializers": [
    "Microsoft.Kiota.Serialization.Json.JsonParseNodeFactory",
    "Microsoft.Kiota.Serialization.Text.TextParseNodeFactory",
    "Microsoft.Kiota.Serialization.Form.FormParseNodeFactory"
  ],
  "structuredMimeTypes": [
    "application/json",
    "text/plain;q=0.9",
    "application/x-www-form-urlencoded;q=0.2",
    "multipart/form-data;q=0.1"
  ],
  "includePatterns": [],
  "excludePatterns": [],
  "disabledValidationRules": []
}